{
  "Appearance": {
    "Model": "Cosmetics/Overtops/Scavenger_Poncho.blockymodel",
    "TextureConfig": {
      "Type": "Static",
      "Texture": "Characters/Custom/Overcoat/Halaster_Poncho_Texture.png"
    }
  },
  "Icon": "Icons/Wardrobe/CosmeticsGenerated/Cosmetic_Halaster_Over.png",
  "CosmeticSlot": "Overtop",
  "Properties": {
    "Translation": {
      "Name": "Halaster Overcoat"
    }
  },
  "IconProperties": {
    "Scale": 0.5,
    "Rotation": [
      22.5,
      45,
      22.5
    ],
    "Translation": [
      0,
      -59
    ]
  }
}
