{
  "Properties": {
    "Translation": {
      "Name": "Bulky Beanie"
    }
  },
  "Appearance": {
    "Model": "Cosmetics/Head/Bulky_Beanie.blockymodel",
    "TextureConfig": {
      "Type": "Gradient",
      "GrayscaleTexture": "Cosmetics/Head/Bulky_Beanie_Textures/Bulky_Beanie_Greyscale.png",
      "GradientSet": "Colored_Cotton"
    }
  },
  "CosmeticSlot": "HeadAccessory",
  "Icon": "Icons/Wardrobe/CosmeticsGenerated/Head_BulkyBeanie.png",
  "IconProperties": {
    "Scale": 0.6,
    "Rotation": [
      22.5,
      45,
      22.5
    ],
    "Translation": [
      0,
      -10
    ]
  }
}
