{
  "Properties": {
    "Translation": {
      "Name": "Ribbed"
    }
  },
  "Appearance": {
    "Model": "Cosmetics/Undertops/LongSleeveShirt.blockymodel",
    "TextureConfig": {
      "Type": "Gradient",
      "GrayscaleTexture": "Cosmetics/Undertops/LongSleeveShirt_Textures/Ribbed_Shirt_Greyscale.png",
      "GradientSet": "Colored_Cotton"
    }
  },
  "Icon": "Icons/Wardrobe/CosmeticsGenerated/UnderTop_Ribbed.png",
  "IconProperties": {
    "Scale": 0.5,
    "Rotation": [
      22.5,
      45,
      22.5
    ],
    "Translation": [
      2,
      -60
    ]
  },
  "CosmeticSlot": "Undertop"
}
