{
  "Properties": {
    "Translation": {
      "Name": "Races_Vanilla_Balding"
    }
  },
  "CosmeticSlot": "Haircut",
  "Appearance": {
    "Model": "Characters/Haircuts/Balding.blockymodel",
    "TextureConfig": {
      "Type": "Gradient",
      "GradientSet": "Hair",
      "GrayscaleTexture": "Characters/Haircuts/Balding_Greyscale.png"
    }
  },
  "Icon": "Icons/Wardrobe/CosmeticsGenerated/Balding.png",
  "IconProperties": {
    "Scale": 0.4,
    "Rotation": [
      22.5,
      45,
      22.5
    ],
    "Translation": [
      0,
      -89
    ]
  }
}
